{
  "_id": "37e26adb5eb7cc580070282b3975f3ae",
  "collectionName": "hiface-configs",
  "description": "配置，可以更改小程序上的页面表现",
  "fields": [
    {
      "fieldLabel": "名称",
      "fieldName": "name",
      "fieldType": "String",
      "isRequired": true
    },
    {
      "fieldLabel": "排序",
      "fieldName": "order",
      "fieldType": "Number",
      "helpText": "值越大在 CMS 列表中越靠前"
    },
    {
      "fieldName": "createTime",
      "fieldType": "DateTime",
      "helpText": "留空时会在服务端自动写入创建时间",
      "fieldLabel": "创建时间"
    },
    {
      "fieldLabel": "修改时间",
      "fieldName": "updateTime",
      "fieldType": "DateTime",
      "helpText": "留空时会在服务端自动写入修改时间"
    },
    {
      "helpText": "请填写JSON格式的字符串",
      "isRequired": true,
      "fieldLabel": "配置内容",
      "fieldName": "content",
      "fieldType": "String"
    }
  ],
  "label": "配置项",
  "id": "37e26adb5eb7cc580070282b3975f3ae"
}